README.txt
setup.py
pyblish_modo/__init__.py
pyblish_modo/lib.py
pyblish_modo/version.py
pyblish_modo.egg-info/PKG-INFO
pyblish_modo.egg-info/SOURCES.txt
pyblish_modo.egg-info/dependency_links.txt
pyblish_modo.egg-info/not-zip-safe
pyblish_modo.egg-info/top_level.txt
pyblish_modo/nexus_user/nodesync.txt
pyblish_modo/nexus_user/Scripts/PyblishModo/index.CFG
pyblish_modo/nexus_user/Scripts/PyblishModo/pyscripts/pyblishModo.py
pyblish_modo/nexus_user/Scripts/PyblishModo/pyscripts/pyblishPublish.py
pyblish_modo/nexus_user/Scripts/PyblishModo/pyscripts/pyblishValidate.py
pyblish_modo/plugins/__init__.py
pyblish_modo/plugins/select_current_file.py