Metadata-Version: 1.1
Name: pyblish-modo
Version: 0.0.2
Summary: The Foundry Modo Pyblish integration
Home-page: https://github.com/pyblish/pyblish-modo
Author: Marcus Ottosson
Author-email: marcus@abstractfactory.io
License: LGPL
Platform: UNKNOWN
Classifier: Development Status :: 3 - Alpha
Classifier: Intended Audience :: Developers
Classifier: License :: OSI Approved :: GNU Lesser General Public License v3 (LGPLv3)
Classifier: Programming Language :: Python
Classifier: Programming Language :: Python :: 2
Classifier: Programming Language :: Python :: 2.6
Classifier: Programming Language :: Python :: 2.7
Classifier: Topic :: Software Development :: Libraries :: Python Modules
Classifier: Topic :: Utilities
